SymSolver/__init__.py
SymSolver/attributors.py
SymSolver/defaults.py
SymSolver/errors.py
SymSolver/initializers.py
SymSolver/abstracts/__init__.py
SymSolver/abstracts/_canonical_ordering.py
SymSolver/abstracts/_complexity.py
SymSolver/abstracts/_compress.py
SymSolver/abstracts/_init_modifiers.py
SymSolver/abstracts/abelian_operations.py
SymSolver/abstracts/abstract_operations.py
SymSolver/abstracts/associative_operations.py
SymSolver/abstracts/commutative_operations.py
SymSolver/abstracts/iterable_symbolic_objects.py
SymSolver/abstracts/keyed_symbolic_objects.py
SymSolver/abstracts/operation_containers.py
SymSolver/abstracts/simplifiable_objects.py
SymSolver/abstracts/substitutions.py
SymSolver/abstracts/symbolic_objects.py
SymSolver/basics/__init__.py
SymSolver/basics/_canonical_ordering.py
SymSolver/basics/_cascade.py
SymSolver/basics/_lites.py
SymSolver/basics/_numbers.py
SymSolver/basics/_square_roots.py
SymSolver/basics/_string_rep.py
SymSolver/basics/_sum_collect.py
SymSolver/basics/_sum_collect_greedy.py
SymSolver/basics/_to_python.py
SymSolver/basics/basics_tools.py
SymSolver/basics/equation.py
SymSolver/basics/equation_system.py
SymSolver/basics/power.py
SymSolver/basics/product.py
SymSolver/basics/sum.py
SymSolver/basics/symbols.py
SymSolver/basics/basics_abstracts/__init__.py
SymSolver/basics/basics_abstracts/abstract_products.py
SymSolver/basics_addons/__init__.py
SymSolver/basics_addons/inequality.py
SymSolver/calculus/__init__.py
SymSolver/calculus/derivatives/__init__.py
SymSolver/calculus/derivatives/_vector_derivative_operators.py
SymSolver/calculus/derivatives/common_vector_derivatives.py
SymSolver/calculus/derivatives/derivative.py
SymSolver/calculus/derivatives/derivatives_tools.py
SymSolver/calculus/derivatives/taking_derivatives.py
SymSolver/calculus/derivatives/vector_derivatives.py
SymSolver/essences/__init__.py
SymSolver/essences/essence_combine.py
SymSolver/essences/essence_matches.py
SymSolver/essences/essence_symbols.py
symsolver-2025.6.0.dist-info/LICENSE
symsolver-2025.6.0.dist-info/WHEEL
symsolver-2025.6.0.dist-info/METADATA
symsolver-2025.6.0.dist-info/RECORD
