Metadata-Version: 2.1
Name: SymSolver
Version: 2025.6.0
Summary: Symbolic Solver for systems of linear, differential, vector equations.
Author-email: Sam Evans <sevans7@bu.edu>
Requires-Python: >=3.7
Requires-Dist: numpy ; extra == "all"
Requires-Dist: matplotlib ; extra == "all"
Requires-Dist: mpmath ; extra == "all"
Requires-Dist: IPython ; extra == "all"
Requires-Dist: matplotlib ; extra == "dev_display"
Requires-Dist: IPython ; extra == "dev_display"
Requires-Dist: numpy ; extra == "dev_math"
Requires-Dist: mpmath ; extra == "dev_math"
Project-URL: source-code, https://gitlab.com/Sevans7/symsolver
Provides-Extra: all
Provides-Extra: dev_display
Provides-Extra: dev_math
